BEASTsim/__init__.py
BEASTsim/beast.py
BEASTsim/beast_data.py
BEASTsim/modules/__init__.py
BEASTsim/modules/analysis/__init__.py
BEASTsim/modules/analysis/analysis.py
BEASTsim/modules/analysis/gene_expression_module/__init__.py
BEASTsim/modules/analysis/gene_expression_module/gene_expression_analysis.py
BEASTsim/modules/analysis/spatial_module/__init__.py
BEASTsim/modules/analysis/spatial_module/simulation_analysis.py
BEASTsim/modules/analysis/spatial_module/spatial_analysis.py
BEASTsim/modules/analysis/spatial_module/SVG/SVG_SpatialDE.py
BEASTsim/modules/analysis/spatial_module/SVG/__init__.py
BEASTsim/modules/analysis/spatial_module/cell_mapping/__init__.py
BEASTsim/modules/analysis/spatial_module/cell_mapping/cell2location.py
BEASTsim/modules/analysis/spatial_module/cell_mapping/cell_mapping_analysis.py
BEASTsim/modules/analysis/spatial_module/simulation/__init__.py
BEASTsim/modules/analysis/spatial_module/simulation/plotting_simulation.py
BEASTsim/modules/analysis/spatial_module/simulation/plotting/SVG_plotting.py
BEASTsim/modules/analysis/spatial_module/simulation/plotting/__init__.py
BEASTsim/modules/analysis/spatial_module/simulation/plotting/cell_type_plotting.py
BEASTsim/modules/analysis/spatial_module/simulation/plotting/neighborhood_plotting.py
BEASTsim/modules/analysis/spatial_module/simulation/plotting/similarity_plotting.py
BEASTsim/modules/benchmarking/__init__.py
BEASTsim/modules/benchmarking/benchmarking.py
BEASTsim/modules/benchmarking/simulation/__init__.py
BEASTsim/modules/benchmarking/simulation/simulation_benchmark.py
BEASTsim/modules/benchmarking/simulation/biological_signals/__init__.py
BEASTsim/modules/benchmarking/simulation/biological_signals/biological_signals_benchmark.py
BEASTsim/modules/benchmarking/simulation/biological_signals/count_based_biological_signals.py
BEASTsim/modules/benchmarking/simulation/biological_signals/spatial_biological_signals.py
BEASTsim/modules/benchmarking/simulation/data_properties/__init__.py
beastsim-0.1.5.dist-info/licenses/LICENSE
beastsim-0.1.5.dist-info/METADATA
beastsim-0.1.5.dist-info/WHEEL
beastsim-0.1.5.dist-info/top_level.txt
beastsim-0.1.5.dist-info/RECORD
